aws_container_launcher/__init__.py
aws_container_launcher/_util.py
aws_container_launcher/custom_logger.py
aws_container_launcher/dynamo_db.py
aws_container_launcher/fsx.py
aws_container_launcher/main.py
aws_container_launcher/run_status.py
aws_container_launcher/ec2/__init__.py
aws_container_launcher/ec2/ami_type.py
aws_container_launcher/ec2/architecture.py
aws_container_launcher/ec2/ec2_os.py
aws_container_launcher/ec2/main.py
aws_container_launcher/exception/InstanceDeployingTimeoutException.py
aws_container_launcher/exception/InstanceInitializingTimeoutException.py
aws_container_launcher/exception/__init__.py
aws_container_launcher-4.1.0.dist-info/METADATA
aws_container_launcher-4.1.0.dist-info/WHEEL
aws_container_launcher-4.1.0.dist-info/top_level.txt
aws_container_launcher-4.1.0.dist-info/RECORD
