Metadata-Version: 2.1
Name: aws-container-launcher
Version: 4.1.0
Summary: AWS Container Launcher makes it easy to programmatically run a Docker container in AWS using the Python package for Batch processing, ML jobs, or fast Web server running.
Home-page: https://github.com/kankou-aliaksei/aws-container-launcher
Author: Aliaksei Kankou
Author-email: aliaksei.kankou@gmail.com
Project-URL: Bug Tracker, https://github.com/kankou-aliaksei/aws-container-launcher/issues
Requires-Python: >3.7.0
Requires-Dist: boto3 (>=1.23.10)
Requires-Dist: amazon-ec2-best-instance (>=2.4.1)
